halofactory/__init__.py
halofactory/functional.py
halofactory/initial_condition.py
halofactory/profile.py
halofactory-0.0.2.dist-info/LICENSE
halofactory-0.0.2.dist-info/METADATA
halofactory-0.0.2.dist-info/WHEEL
halofactory-0.0.2.dist-info/top_level.txt
halofactory-0.0.2.dist-info/RECORD
