Metadata-Version: 2.1
Name: halofactory
Version: 0.0.2
Summary: Semi-analytical dark matter halo generator for astrophysics
Author-email: Yangyao Chen <yangyaochen.astro@foxmail.com>, Kai Wang <wkcosmology@gmail.com>
Project-URL: Repository, https://github.com/ChenYangyao/halofactory.git
Classifier: Programming Language :: Python :: 3
Classifier: License :: OSI Approved :: MIT License
Classifier: Operating System :: OS Independent
Requires-Python: >=3.9
License-File: LICENSE
Requires-Dist: pyhipp >=0.0.3
Requires-Dist: scipy
Requires-Dist: numpy
